publish_tools/Dockerfile
publish_tools/__init__.py
publish_tools/ansible_utils.py
publish_tools/docker_utils.py
publish_tools/github_utils.py
publish_tools/mvn_utils.py
publish_tools/npm_utils.py
publish_tools/package-lock.json
publish_tools/package.json
publish_tools/pom.xml
publish_tools/settings.xml
publish_tools/version_utils.py
publish_tools/template/pom.xml
mucsi96_publish_tools-41.0.0.dist-info/METADATA
mucsi96_publish_tools-41.0.0.dist-info/WHEEL
mucsi96_publish_tools-41.0.0.dist-info/licenses/LICENSE
mucsi96_publish_tools-41.0.0.dist-info/RECORD
