Metadata-Version: 2.3
Name: mucsi96.publish_tools
Version: 41.0.0
Summary: Publishing tools for continuous integration
Author-email: Igor Bari <mucsi96@gmail.com>
License-File: LICENSE
Requires-Dist: ansible==9.11.0
Requires-Dist: requests==2.32.3
